gigrator/__init__.py
gigrator/config.py
gigrator/gigrator.py
gigrator/util.py
gigrator/git/__init__.py
gigrator/git/coding.py
gigrator/git/git.py
gigrator/git/gitea.py
gigrator/git/gitee.py
gigrator/git/github.py
gigrator/git/gitlab.py
gigrator/git/gongfeng.py
gigrator-1.0.2.dist-info/LICENSE
gigrator-1.0.2.dist-info/METADATA
gigrator-1.0.2.dist-info/WHEEL
gigrator-1.0.2.dist-info/entry_points.txt
gigrator-1.0.2.dist-info/top_level.txt
gigrator-1.0.2.dist-info/RECORD
