Metadata-Version: 2.1
Name: gigrator
Version: 1.0.2
Summary: Git repositories migration tool
Home-page: https://github.com/k8scat/gigrator
Author: K8sCat
Author-email: k8scat@gmail.com
License: UNKNOWN
Platform: UNKNOWN
Classifier: Programming Language :: Python :: 3
Classifier: License :: OSI Approved :: MIT License
Classifier: Operating System :: OS Independent
Requires-Python: >=3.6
License-File: LICENSE
Requires-Dist: PyYaml
Requires-Dist: requests
